omniifer_api/__init__.py
omniifer_api/config.py
omniifer_api/error.py
omniifer_api/image_generate/__init__.py
omniifer_api/image_generate/img2img.py
omniifer_api/image_generate/progress.py
omniifer_api/image_generate/txt2img.py
omniifer_api/model_list/__init__.py
omniifer_api/model_list/get_model.py
omniifer_api/model_list/get_models.py
omniifer_api/model_list/model_available.py
omniifer_api/model_list/put_model.py
omniifer_api/model_list/search_models.py
omniifer_api/model_list/update.py
omniifer_api/tools/__init__.py
omniifer_api/tools/response_check.py
omniifer_api/upscale/__init__.py
omniifer_api/upscale/upscale.py
omniifer_api/upscale/upscale_data.py
omni_infer_api-0.0.11.dist-info/METADATA
omni_infer_api-0.0.11.dist-info/WHEEL
omni_infer_api-0.0.11.dist-info/top_level.txt
omni_infer_api-0.0.11.dist-info/RECORD
