Metadata-Version: 2.1
Name: omni-infer-api
Version: 0.0.11
Summary: The omni infer ai platform api toolkit
Home-page: 
Author: stay_miku
Author-email: miku@miku.pics
Requires-Dist: requests
Requires-Dist: pillow
